noy_black/Grammar.txt
noy_black/__init__.py
noy_black/main.py
noy_black-0.1.5.dist-info/METADATA
noy_black-0.1.5.dist-info/WHEEL
noy_black-0.1.5.dist-info/entry_points.txt
noy_black-0.1.5.dist-info/top_level.txt
noy_black-0.1.5.dist-info/RECORD
