Metadata-Version: 2.1
Name: noy-black
Version: 0.1.5
Summary: Monkey patched black that understands nose of yeti
Home-page: https://github.com/delfick/noy_black
Author: Stephen Moore
Author-email: delfick755@gmail.com
License: MIT
Platform: UNKNOWN
Requires-Python: >= 3.6
Requires-Dist: black (==19.10b0)
Requires-Dist: noseOfYeti (>=1.9.1)
